{
    "version": "0.0.1",
    "architecture": {
        "64bit": {
            "url": "https://github.com/nsnarender5511/crules/releases/download/v0.0.1/crules_windows_amd64.tar.gz",
            "bin": [
                "crules.exe"
            ],
            "hash": "f89d9e4ec39e38c612921337eeb5e75158e31872b2abdd793b425d9e9ec5304c"
        },
        "arm64": {
            "url": "https://github.com/nsnarender5511/crules/releases/download/v0.0.1/crules_windows_arm64.tar.gz",
            "bin": [
                "crules.exe"
            ],
            "hash": "2bae4774746df12d01965adf63bcdb3915cb8b0b80f2845044987b7ec7fba002"
        }
    },
    "homepage": "https://github.com/nsnarender5511/crules",
    "license": "MIT",
    "description": "A tool for managing and synchronizing Cursor rules across multiple projects"
}